dspy_tool/__init__.py
dspy_tool/cli/css.tcss
dspy_tool/cli/dsp_codec.py
dspy_tool/cli/file_manager.py
dspy_tool/cli/utils/config/config.py
dspy_tool/cli/utils/config/fm_config.py
dspy_tool/dsp_codec/__init__.py
dspy_tool/dsp_codec/file.py
dspy_tool/dsp_codec/internal/__init__.py
dspy_tool/dsp_codec/internal/attribute.py
dspy_tool/dsp_codec/internal/code.py
dspy_tool/dsp_codec/internal/code_type.py
dspy_tool/dsp_codec/internal/dji.py
dspy_tool/dsp_codec/internal/fvd.py
dspy_tool-0.1.1.dist-info/entry_points.txt
dspy_tool-0.1.1.dist-info/LICENSE
dspy_tool-0.1.1.dist-info/WHEEL
dspy_tool-0.1.1.dist-info/METADATA
dspy_tool-0.1.1.dist-info/RECORD
