Metadata-Version: 2.1
Name: dspy_tool
Version: 0.1.1
Summary: DJI DSP Tools for Python
Author-email: cranyozen <cranyozen@foxmail.com>
Requires-Python: >=3.8
Classifier: Programming Language :: Python :: 3
Classifier: Development Status :: 2 - Pre-Alpha
Classifier: License :: OSI Approved :: GNU General Public License v2 (GPLv2)
Requires-Dist: pycryptodome >= 3.19
Requires-Dist: pyyaml >= 6.0.1
Requires-Dist: textual[syntax] >= 0.58.0
Requires-Dist: pyperclip >= 1.8.2
Project-URL: Home, https://github.com/
